textbasedbattlesystem/__init__.py
textbasedbattlesystem/battle.py
textbasedbattlesystem-0.1.1.dist-info/licenses/LICENSE
textbasedbattlesystem-0.1.1.dist-info/METADATA
textbasedbattlesystem-0.1.1.dist-info/WHEEL
textbasedbattlesystem-0.1.1.dist-info/top_level.txt
textbasedbattlesystem-0.1.1.dist-info/RECORD
