Metadata-Version: 2.4
Name: textbasedbattlesystem
Version: 0.1.1
Summary: Text Based Battle System
Author: patatesadamsfriend
License: MIT License
Requires-Python: >=3.8
License-File: LICENSE
Dynamic: license-file
